README.md
setup.py
henrietta/__init__.py
henrietta/fitting.py
henrietta/goodnesses.py
henrietta/imports.py
henrietta/lightcurves.py
henrietta/mcmc.py
henrietta/modeling.py
henrietta/optimizers.py
henrietta/statistics.py
henrietta/tools.py
henrietta/tpf.py
henrietta/utilities.py
henrietta/version.py
henrietta.egg-info/PKG-INFO
henrietta.egg-info/SOURCES.txt
henrietta.egg-info/dependency_links.txt
henrietta.egg-info/not-zip-safe
henrietta.egg-info/requires.txt
henrietta.egg-info/top_level.txt
henrietta/imaging/__init__.py
henrietta/imaging/io.py
henrietta/imaging/simulations.py
henrietta/imaging/visualize.py
henrietta/photometry/__init__.py
henrietta/photometry/apertures.py
henrietta/photometry/cartoons.py
henrietta/photometry/centroid.py
henrietta/photometry/loupe.py
henrietta/photometry/photometry.py
henrietta/photometry/photometry_plot.py
henrietta/tests/__init__.py
henrietta/tests/test_centroid.py
henrietta/tests/test_fitting.py
henrietta/tests/test_imaging.py
henrietta/tests/test_lightcurves.py
henrietta/tests/test_models.py
henrietta/tests/test_photometry.py
henrietta/tests/test_statistics.py
henrietta/tests/test_tools.py
henrietta/tests/test_tpf.py