Metadata-Version: 2.1
Name: henrietta
Version: 1.0.3
Summary: Python toolkit playing with stellar brightness measurements, for ASTR3400 at CU Boulder.
Home-page: https://github.com/zkbt/henrietta
Author: Zach Berta-Thompson
Author-email: zach.bertathompson@colorado.edu
License: MIT
Platform: UNKNOWN
Classifier: Intended Audience :: Education
Classifier: Intended Audience :: Science/Research
Classifier: Programming Language :: Python
Classifier: Topic :: Scientific/Engineering :: Astronomy
Provides-Extra: models
Provides-Extra: docs
